PypStat/_PyStats.py
PypStat/__init__.py
PypStat/errors.py
PypStat/utilities.py
PypStat-1.2.dist-info/LICENSE
PypStat-1.2.dist-info/METADATA
PypStat-1.2.dist-info/WHEEL
PypStat-1.2.dist-info/entry_points.txt
PypStat-1.2.dist-info/top_level.txt
PypStat-1.2.dist-info/RECORD
