Metadata-Version: 2.1
Name: PypStat
Version: 1.2
Summary: PyStats is a python module that allows you to easily view your python statistics, Using your dataset
Author-email: Nonja N Astro <anantakshg@gmail.com>
License: GNU GENERAL PUBLIC LICENSE
Project-URL: Homepage, https://github.com/DamnUi/PyStats/
Project-URL: Bug Tracker, https://github.com/DamnUi/PyStats/issues
Classifier: Programming Language :: Python :: 3
Classifier: License :: OSI Approved :: MIT License
Classifier: Operating System :: OS Independent
Requires-Python: >=3.7
License-File: LICENSE
Requires-Dist: rich (>=12.0.0)
